{
    "NFT_1": {
        "name": "NFT_1",
        "arkaplan": "arkaplan2.png",
        "arkaplan hue": 490,
        "goz": "goz1.png",
        "goz hue": 140,
        "kas": "kas3.png",
        "kas hue": 10,
        "agiz": "agiz1.png",
        "agiz hue": 50
    },
    "NFT_2": {
        "name": "NFT_2",
        "arkaplan": "arkaplan1.png",
        "arkaplan hue": 330,
        "goz": "goz2.png",
        "goz hue": 120,
        "kas": "kas1.png",
        "kas hue": 450,
        "agiz": "agiz3.png",
        "agiz hue": 350
    },
    "NFT_3": {
        "name": "NFT_3",
        "arkaplan": "arkaplan2.png",
        "arkaplan hue": 340,
        "goz": "goz1.png",
        "goz hue": 300,
        "kas": "kas2.png",
        "kas hue": 420,
        "agiz": "agiz3.png",
        "agiz hue": 10
    },
    "NFT_4": {
        "name": "NFT_4",
        "arkaplan": "arkaplan1.png",
        "arkaplan hue": 380,
        "goz": "goz3.png",
        "goz hue": 500,
        "kas": "kas1.png",
        "kas hue": 200,
        "agiz": "agiz3.png",
        "agiz hue": 180
    },
    "NFT_5": {
        "name": "NFT_5",
        "arkaplan": "arkaplan3.png",
        "arkaplan hue": 320,
        "goz": "goz3.png",
        "goz hue": 420,
        "kas": "kas2.png",
        "kas hue": 80,
        "agiz": "agiz1.png",
        "agiz hue": 170
    },
    "NFT_6": {
        "name": "NFT_6",
        "arkaplan": "arkaplan3.png",
        "arkaplan hue": 450,
        "goz": "goz2.png",
        "goz hue": 280,
        "kas": "kas1.png",
        "kas hue": 250,
        "agiz": "agiz3.png",
        "agiz hue": 260
    },
    "NFT_7": {
        "name": "NFT_7",
        "arkaplan": "arkaplan3.png",
        "arkaplan hue": 240,
        "goz": "goz3.png",
        "goz hue": 410,
        "kas": "kas2.png",
        "kas hue": 240,
        "agiz": "agiz3.png",
        "agiz hue": 40
    },
    "NFT_8": {
        "name": "NFT_8",
        "arkaplan": "arkaplan2.png",
        "arkaplan hue": 300,
        "goz": "goz1.png",
        "goz hue": 100,
        "kas": "kas3.png",
        "kas hue": 400,
        "agiz": "agiz1.png",
        "agiz hue": 320
    },
    "NFT_9": {
        "name": "NFT_9",
        "arkaplan": "arkaplan3.png",
        "arkaplan hue": 150,
        "goz": "goz3.png",
        "goz hue": 240,
        "kas": "kas2.png",
        "kas hue": 260,
        "agiz": "agiz2.png",
        "agiz hue": 270
    },
    "NFT_10": {
        "name": "NFT_10",
        "arkaplan": "arkaplan1.png",
        "arkaplan hue": 340,
        "goz": "goz3.png",
        "goz hue": 330,
        "kas": "kas3.png",
        "kas hue": 190,
        "agiz": "agiz2.png",
        "agiz hue": 180
    },
    "NFT_11": {
        "name": "NFT_11",
        "arkaplan": "arkaplan2.png",
        "arkaplan hue": 410,
        "goz": "goz3.png",
        "goz hue": 260,
        "kas": "kas1.png",
        "kas hue": 130,
        "agiz": "agiz1.png",
        "agiz hue": 390
    },
    "NFT_12": {
        "name": "NFT_12",
        "arkaplan": "arkaplan2.png",
        "arkaplan hue": 60,
        "goz": "goz3.png",
        "goz hue": 460,
        "kas": "kas3.png",
        "kas hue": 30,
        "agiz": "agiz1.png",
        "agiz hue": 490
    },
    "NFT_13": {
        "name": "NFT_13",
        "arkaplan": "arkaplan2.png",
        "arkaplan hue": 280,
        "goz": "goz2.png",
        "goz hue": 240,
        "kas": "kas3.png",
        "kas hue": 500,
        "agiz": "agiz1.png",
        "agiz hue": 160
    },
    "NFT_14": {
        "name": "NFT_14",
        "arkaplan": "arkaplan1.png",
        "arkaplan hue": 80,
        "goz": "goz2.png",
        "goz hue": 490,
        "kas": "kas3.png",
        "kas hue": 410,
        "agiz": "agiz3.png",
        "agiz hue": 400
    },
    "NFT_15": {
        "name": "NFT_15",
        "arkaplan": "arkaplan1.png",
        "arkaplan hue": 290,
        "goz": "goz3.png",
        "goz hue": 370,
        "kas": "kas3.png",
        "kas hue": 150,
        "agiz": "agiz2.png",
        "agiz hue": 240
    },
    "NFT_16": {
        "name": "NFT_16",
        "arkaplan": "arkaplan2.png",
        "arkaplan hue": 370,
        "goz": "goz2.png",
        "goz hue": 10,
        "kas": "kas2.png",
        "kas hue": 380,
        "agiz": "agiz3.png",
        "agiz hue": 200
    },
    "NFT_17": {
        "name": "NFT_17",
        "arkaplan": "arkaplan2.png",
        "arkaplan hue": 70,
        "goz": "goz3.png",
        "goz hue": 460,
        "kas": "kas3.png",
        "kas hue": 310,
        "agiz": "agiz1.png",
        "agiz hue": 260
    },
    "NFT_18": {
        "name": "NFT_18",
        "arkaplan": "arkaplan2.png",
        "arkaplan hue": 50,
        "goz": "goz3.png",
        "goz hue": 80,
        "kas": "kas1.png",
        "kas hue": 160,
        "agiz": "agiz3.png",
        "agiz hue": 30
    },
    "NFT_19": {
        "name": "NFT_19",
        "arkaplan": "arkaplan2.png",
        "arkaplan hue": 220,
        "goz": "goz2.png",
        "goz hue": 310,
        "kas": "kas2.png",
        "kas hue": 30,
        "agiz": "agiz3.png",
        "agiz hue": 360
    },
    "NFT_20": {
        "name": "NFT_20",
        "arkaplan": "arkaplan1.png",
        "arkaplan hue": 360,
        "goz": "goz3.png",
        "goz hue": 270,
        "kas": "kas3.png",
        "kas hue": 460,
        "agiz": "agiz1.png",
        "agiz hue": 260
    },
    "NFT_21": {
        "name": "NFT_21",
        "arkaplan": "arkaplan2.png",
        "arkaplan hue": 340,
        "goz": "goz2.png",
        "goz hue": 180,
        "kas": "kas1.png",
        "kas hue": 370,
        "agiz": "agiz1.png",
        "agiz hue": 30
    },
    "NFT_22": {
        "name": "NFT_22",
        "arkaplan": "arkaplan2.png",
        "arkaplan hue": 220,
        "goz": "goz3.png",
        "goz hue": 300,
        "kas": "kas1.png",
        "kas hue": 220,
        "agiz": "agiz2.png",
        "agiz hue": 270
    },
    "NFT_23": {
        "name": "NFT_23",
        "arkaplan": "arkaplan2.png",
        "arkaplan hue": 220,
        "goz": "goz2.png",
        "goz hue": 450,
        "kas": "kas3.png",
        "kas hue": 10,
        "agiz": "agiz1.png",
        "agiz hue": 20
    },
    "NFT_24": {
        "name": "NFT_24",
        "arkaplan": "arkaplan2.png",
        "arkaplan hue": 260,
        "goz": "goz3.png",
        "goz hue": 160,
        "kas": "kas2.png",
        "kas hue": 100,
        "agiz": "agiz1.png",
        "agiz hue": 240
    },
    "NFT_25": {
        "name": "NFT_25",
        "arkaplan": "arkaplan1.png",
        "arkaplan hue": 410,
        "goz": "goz1.png",
        "goz hue": 390,
        "kas": "kas3.png",
        "kas hue": 380,
        "agiz": "agiz2.png",
        "agiz hue": 210
    },
    "NFT_26": {
        "name": "NFT_26",
        "arkaplan": "arkaplan2.png",
        "arkaplan hue": 420,
        "goz": "goz1.png",
        "goz hue": 60,
        "kas": "kas2.png",
        "kas hue": 360,
        "agiz": "agiz1.png",
        "agiz hue": 200
    },
    "NFT_27": {
        "name": "NFT_27",
        "arkaplan": "arkaplan2.png",
        "arkaplan hue": 270,
        "goz": "goz3.png",
        "goz hue": 330,
        "kas": "kas2.png",
        "kas hue": 500,
        "agiz": "agiz1.png",
        "agiz hue": 320
    },
    "NFT_28": {
        "name": "NFT_28",
        "arkaplan": "arkaplan3.png",
        "arkaplan hue": 480,
        "goz": "goz3.png",
        "goz hue": 360,
        "kas": "kas3.png",
        "kas hue": 290,
        "agiz": "agiz1.png",
        "agiz hue": 270
    },
    "NFT_29": {
        "name": "NFT_29",
        "arkaplan": "arkaplan3.png",
        "arkaplan hue": 500,
        "goz": "goz3.png",
        "goz hue": 110,
        "kas": "kas3.png",
        "kas hue": 140,
        "agiz": "agiz2.png",
        "agiz hue": 340
    },
    "NFT_30": {
        "name": "NFT_30",
        "arkaplan": "arkaplan3.png",
        "arkaplan hue": 50,
        "goz": "goz1.png",
        "goz hue": 180,
        "kas": "kas3.png",
        "kas hue": 240,
        "agiz": "agiz1.png",
        "agiz hue": 110
    },
    "NFT_31": {
        "name": "NFT_31",
        "arkaplan": "arkaplan1.png",
        "arkaplan hue": 50,
        "goz": "goz3.png",
        "goz hue": 410,
        "kas": "kas1.png",
        "kas hue": 280,
        "agiz": "agiz3.png",
        "agiz hue": 250
    },
    "NFT_32": {
        "name": "NFT_32",
        "arkaplan": "arkaplan1.png",
        "arkaplan hue": 140,
        "goz": "goz1.png",
        "goz hue": 120,
        "kas": "kas3.png",
        "kas hue": 100,
        "agiz": "agiz2.png",
        "agiz hue": 170
    },
    "NFT_33": {
        "name": "NFT_33",
        "arkaplan": "arkaplan1.png",
        "arkaplan hue": 280,
        "goz": "goz1.png",
        "goz hue": 250,
        "kas": "kas3.png",
        "kas hue": 430,
        "agiz": "agiz1.png",
        "agiz hue": 440
    },
    "NFT_34": {
        "name": "NFT_34",
        "arkaplan": "arkaplan1.png",
        "arkaplan hue": 430,
        "goz": "goz1.png",
        "goz hue": 240,
        "kas": "kas1.png",
        "kas hue": 230,
        "agiz": "agiz2.png",
        "agiz hue": 340
    },
    "NFT_35": {
        "name": "NFT_35",
        "arkaplan": "arkaplan3.png",
        "arkaplan hue": 410,
        "goz": "goz2.png",
        "goz hue": 480,
        "kas": "kas1.png",
        "kas hue": 320,
        "agiz": "agiz2.png",
        "agiz hue": 300
    },
    "NFT_36": {
        "name": "NFT_36",
        "arkaplan": "arkaplan3.png",
        "arkaplan hue": 380,
        "goz": "goz2.png",
        "goz hue": 400,
        "kas": "kas2.png",
        "kas hue": 350,
        "agiz": "agiz3.png",
        "agiz hue": 200
    },
    "NFT_37": {
        "name": "NFT_37",
        "arkaplan": "arkaplan3.png",
        "arkaplan hue": 450,
        "goz": "goz3.png",
        "goz hue": 350,
        "kas": "kas2.png",
        "kas hue": 120,
        "agiz": "agiz1.png",
        "agiz hue": 500
    },
    "NFT_38": {
        "name": "NFT_38",
        "arkaplan": "arkaplan1.png",
        "arkaplan hue": 10,
        "goz": "goz1.png",
        "goz hue": 400,
        "kas": "kas2.png",
        "kas hue": 110,
        "agiz": "agiz1.png",
        "agiz hue": 270
    },
    "NFT_39": {
        "name": "NFT_39",
        "arkaplan": "arkaplan3.png",
        "arkaplan hue": 280,
        "goz": "goz2.png",
        "goz hue": 200,
        "kas": "kas2.png",
        "kas hue": 20,
        "agiz": "agiz1.png",
        "agiz hue": 120
    },
    "NFT_40": {
        "name": "NFT_40",
        "arkaplan": "arkaplan3.png",
        "arkaplan hue": 450,
        "goz": "goz3.png",
        "goz hue": 480,
        "kas": "kas1.png",
        "kas hue": 120,
        "agiz": "agiz1.png",
        "agiz hue": 220
    },
    "NFT_41": {
        "name": "NFT_41",
        "arkaplan": "arkaplan3.png",
        "arkaplan hue": 160,
        "goz": "goz1.png",
        "goz hue": 290,
        "kas": "kas1.png",
        "kas hue": 310,
        "agiz": "agiz2.png",
        "agiz hue": 180
    },
    "NFT_42": {
        "name": "NFT_42",
        "arkaplan": "arkaplan1.png",
        "arkaplan hue": 190,
        "goz": "goz1.png",
        "goz hue": 440,
        "kas": "kas3.png",
        "kas hue": 60,
        "agiz": "agiz1.png",
        "agiz hue": 250
    },
    "NFT_43": {
        "name": "NFT_43",
        "arkaplan": "arkaplan1.png",
        "arkaplan hue": 60,
        "goz": "goz1.png",
        "goz hue": 100,
        "kas": "kas2.png",
        "kas hue": 230,
        "agiz": "agiz3.png",
        "agiz hue": 90
    },
    "NFT_44": {
        "name": "NFT_44",
        "arkaplan": "arkaplan2.png",
        "arkaplan hue": 90,
        "goz": "goz3.png",
        "goz hue": 250,
        "kas": "kas2.png",
        "kas hue": 390,
        "agiz": "agiz3.png",
        "agiz hue": 300
    },
    "NFT_45": {
        "name": "NFT_45",
        "arkaplan": "arkaplan3.png",
        "arkaplan hue": 100,
        "goz": "goz2.png",
        "goz hue": 310,
        "kas": "kas1.png",
        "kas hue": 240,
        "agiz": "agiz3.png",
        "agiz hue": 450
    },
    "NFT_46": {
        "name": "NFT_46",
        "arkaplan": "arkaplan2.png",
        "arkaplan hue": 370,
        "goz": "goz3.png",
        "goz hue": 40,
        "kas": "kas3.png",
        "kas hue": 120,
        "agiz": "agiz1.png",
        "agiz hue": 200
    },
    "NFT_47": {
        "name": "NFT_47",
        "arkaplan": "arkaplan1.png",
        "arkaplan hue": 420,
        "goz": "goz2.png",
        "goz hue": 410,
        "kas": "kas1.png",
        "kas hue": 140,
        "agiz": "agiz2.png",
        "agiz hue": 30
    },
    "NFT_48": {
        "name": "NFT_48",
        "arkaplan": "arkaplan1.png",
        "arkaplan hue": 110,
        "goz": "goz1.png",
        "goz hue": 260,
        "kas": "kas1.png",
        "kas hue": 130,
        "agiz": "agiz1.png",
        "agiz hue": 390
    },
    "NFT_49": {
        "name": "NFT_49",
        "arkaplan": "arkaplan3.png",
        "arkaplan hue": 460,
        "goz": "goz2.png",
        "goz hue": 250,
        "kas": "kas3.png",
        "kas hue": 470,
        "agiz": "agiz3.png",
        "agiz hue": 230
    },
    "NFT_50": {
        "name": "NFT_50",
        "arkaplan": "arkaplan1.png",
        "arkaplan hue": 200,
        "goz": "goz3.png",
        "goz hue": 380,
        "kas": "kas1.png",
        "kas hue": 40,
        "agiz": "agiz2.png",
        "agiz hue": 240
    }
}